README.rst
setup.py
option_merge/__init__.py
option_merge/collector.py
option_merge/converter.py
option_merge/formatter.py
option_merge/helper.py
option_merge/joiner.py
option_merge/merge.py
option_merge/not_found.py
option_merge/path.py
option_merge/storage.py
option_merge/value_at.py
option_merge/versioning.py
option_merge.egg-info/PKG-INFO
option_merge.egg-info/SOURCES.txt
option_merge.egg-info/dependency_links.txt
option_merge.egg-info/requires.txt
option_merge.egg-info/top_level.txt