Metadata-Version: 1.0
Name: option-merge
Version: 1.5
Summary: Code to deeply merge multiple python dictionaries
Home-page: http://github.com/delfick/option_merge
Author: Stephen Moore
Author-email: stephen@delfick.com
License: WTFPL
Keywords: deep merge
Platform: UNKNOWN
